genesis_notification/__init__.py
genesis_notification/version.py
genesis_notification/clients/__init__.py
genesis_notification/clients/iam.py
genesis_notification/cmd/__init__.py
genesis_notification/cmd/builder_agent.py
genesis_notification/cmd/mail_agent.py
genesis_notification/cmd/user_api.py
genesis_notification/common/__init__.py
genesis_notification/common/config.py
genesis_notification/common/constants.py
genesis_notification/common/log.py
genesis_notification/common/api/__init__.py
genesis_notification/common/api/middlewares/__init__.py
genesis_notification/common/api/middlewares/errors.py
genesis_notification/dm/__init__.py
genesis_notification/dm/models.py
genesis_notification/services/__init__.py
genesis_notification/services/builders/__init__.py
genesis_notification/services/builders/agents.py
genesis_notification/services/providers/agents.py
genesis_notification/tests/__init__.py
genesis_notification/tests/functional/__init__.py
genesis_notification/tests/functional/test_basic.py
genesis_notification/tests/unit/__init__.py
genesis_notification/tests/unit/test_basic.py
genesis_notification/user_api/__init__.py
genesis_notification/user_api/api/__init__.py
genesis_notification/user_api/api/app.py
genesis_notification/user_api/api/controllers.py
genesis_notification/user_api/api/routes.py
genesis_notification/user_api/api/versions.py
genesis_notification-0.3.0.dist-info/licenses/AUTHORS
genesis_notification-0.3.0.dist-info/licenses/LICENSE
genesis_notification-0.3.0.dist-info/METADATA
genesis_notification-0.3.0.dist-info/WHEEL
genesis_notification-0.3.0.dist-info/entry_points.txt
genesis_notification-0.3.0.dist-info/pbr.json
genesis_notification-0.3.0.dist-info/top_level.txt
genesis_notification-0.3.0.dist-info/RECORD
