Metadata-Version: 2.4
Name: genesis_notification
Version: 0.3.0
Summary: The Platform Notification summary
Home-page: https://github.com/infraguys/genesis_notification/
Author: Genesis Corporation
Author-email: eugene@frolov.net.ru
Classifier: Intended Audience :: Developers
Classifier: License :: OSI Approved :: Apache Software License
Classifier: Operating System :: POSIX :: Linux
Classifier: Programming Language :: Python
Classifier: Programming Language :: Python :: 3
Classifier: Programming Language :: Python :: 3.8
Classifier: Programming Language :: Python :: 3.10
Classifier: Programming Language :: Python :: 3.11
Classifier: Programming Language :: Python :: 3.12
Classifier: Programming Language :: Python :: 3.13
License-File: LICENSE
License-File: AUTHORS
Requires-Dist: pbr<=5.8.1,>=1.10.0
Requires-Dist: oslo.config<10.0.0,>=3.22.2
Requires-Dist: restalchemy<15.0.0,>=14.1.0
Requires-Dist: gcl_iam<1.0.0,>=0.8.0
Requires-Dist: gcl_looper<=1.0.0,>=0.1.0
Requires-Dist: bjoern>=3.2.2
Requires-Dist: Jinja2<4.0.0,>=3.1.5
Requires-Dist: bazooka<2.0.0,>=1.3.0
Requires-Dist: zulip<1.0.0,>=0.9.0
Dynamic: author
Dynamic: author-email
Dynamic: classifier
Dynamic: description
Dynamic: home-page
Dynamic: license-file
Dynamic: requires-dist
Dynamic: summary
